{
    "T676P": {
        "id": 65,
        "pos": 676,
        "ref": "T",
        "alt": "P",
        "target": "benign",
        "count": 1,
        "n_pos": 2180,
        "d_to_active_site": 20.352081298828125,
        "d_to_ATP_site": 29.043182373046875,
        "d_to_mg_site_1": 26.803220748901367,
        "d_to_mg_site_2": 23.061859130859375,
        "consurf": -0.372,
        "p_con": 0.9912950054937786,
        "n_con": 1.0,
        "sol_acc": 92,
        "ref_prop": 1,
        "alt_prop": 2,
        "exon": 15,
        "pfam_domain": 0,
        "rel_freq": 0.0033783783783783786
    },
    "V642I": {
        "id": 66,
        "pos": 642,
        "ref": "V",
        "alt": "I",
        "target": "benign",
        "count": 8,
        "n_pos": 2078,
        "d_to_active_site": 32.650875091552734,
        "d_to_ATP_site": 32.653133392333984,
        "d_to_mg_site_1": 39.78386306762695,
        "d_to_mg_site_2": 37.93095016479492,
        "consurf": -0.412,
        "p_con": 0.9844463990879841,
        "n_con": 0.9793597659404568,
        "sol_acc": 152,
        "ref_prop": 2,
        "alt_prop": 2,
        "exon": 14,
        "pfam_domain": 0,
        "rel_freq": 0.02702702702702703
    },
    "V679I": {
        "id": 67,
        "pos": 679,
        "ref": "V",
        "alt": "I",
        "target": "benign",
        "count": 1,
        "n_pos": 2189,
        "d_to_active_site": 17.692583084106445,
        "d_to_ATP_site": 28.284849166870117,
        "d_to_mg_site_1": 24.80795669555664,
        "d_to_mg_site_2": 22.88351058959961,
        "consurf": -0.474,
        "p_con": 0.9912950054937786,
        "n_con": 0.963062304805557,
        "sol_acc": 60,
        "ref_prop": 2,
        "alt_prop": 2,
        "exon": 15,
        "pfam_domain": 0,
        "rel_freq": 0.0033783783783783786
    },
    "R507C": {
        "id": 68,
        "pos": 507,
        "ref": "R",
        "alt": "C",
        "target": "benign",
        "count": 2,
        "n_pos": 1673,
        "d_to_active_site": 22.729873657226562,
        "d_to_ATP_site": 9.11920166015625,
        "d_to_mg_site_1": 25.061363220214844,
        "d_to_mg_site_2": 23.277450561523438,
        "consurf": -0.084,
        "p_con": 0.9672737399983267,
        "n_con": 0.963062304805557,
        "sol_acc": 2,
        "ref_prop": 0,
        "alt_prop": 1,
        "exon": 12,
        "pfam_domain": 1,
        "rel_freq": 0.006756756756756757
    },
    "A635T": {
        "id": 69,
        "pos": 635,
        "ref": "A",
        "alt": "T",
        "target": "benign",
        "count": 1,
        "n_pos": 2057,
        "d_to_active_site": 22.84185218811035,
        "d_to_ATP_site": 24.591812133789062,
        "d_to_mg_site_1": 30.132871627807617,
        "d_to_mg_site_2": 27.981239318847656,
        "consurf": -0.476,
        "p_con": 1.0,
        "n_con": 0.9793597659404568,
        "sol_acc": 83,
        "ref_prop": 2,
        "alt_prop": 1,
        "exon": 14,
        "pfam_domain": 0,
        "rel_freq": 0.0033783783783783786
    },
    "A636T": {
        "id": 70,
        "pos": 636,
        "ref": "A",
        "alt": "T",
        "target": "benign",
        "count": 6,
        "n_pos": 2060,
        "d_to_active_site": 23.516067504882812,
        "d_to_ATP_site": 26.788904190063477,
        "d_to_mg_site_1": 30.849714279174805,
        "d_to_mg_site_2": 29.403793334960938,
        "consurf": 0.365,
        "p_con": 0.9499232831949368,
        "n_con": 0.9587339727429023,
        "sol_acc": 44,
        "ref_prop": 2,
        "alt_prop": 1,
        "exon": 14,
        "pfam_domain": 0,
        "rel_freq": 0.02027027027027027
    },
    "R230W": {
        "id": 71,
        "pos": 230,
        "ref": "R",
        "alt": "W",
        "target": "benign",
        "count": 1,
        "n_pos": 842,
        "d_to_active_site": 35.82102584838867,
        "d_to_ATP_site": 32.495601654052734,
        "d_to_mg_site_1": 30.459320068359375,
        "d_to_mg_site_2": 28.398313522338867,
        "consurf": -0.167,
        "p_con": 0.9912950054937786,
        "n_con": 0.9344467352088275,
        "sol_acc": 15,
        "ref_prop": 0,
        "alt_prop": 1,
        "exon": 7,
        "pfam_domain": 1,
        "rel_freq": 0.0033783783783783786
    },
    "R64Q": {
        "id": 72,
        "pos": 64,
        "ref": "R",
        "alt": "Q",
        "target": "benign",
        "count": 2,
        "n_pos": 345,
        "d_to_active_site": 41.59765625,
        "d_to_ATP_site": 40.867286682128906,
        "d_to_mg_site_1": 34.12901306152344,
        "d_to_mg_site_2": 37.1763801574707,
        "consurf": -0.451,
        "p_con": 1.0,
        "n_con": 0.978205952130997,
        "sol_acc": 3,
        "ref_prop": 0,
        "alt_prop": 1,
        "exon": 4,
        "pfam_domain": 1,
        "rel_freq": 0.006756756756756757
    },
    "G398R": {
        "id": 73,
        "pos": 398,
        "ref": "G",
        "alt": "R",
        "target": "benign",
        "count": 1,
        "n_pos": 1346,
        "d_to_active_site": 29.75661849975586,
        "d_to_ATP_site": 29.319726943969727,
        "d_to_mg_site_1": 29.2324275970459,
        "d_to_mg_site_2": 33.779937744140625,
        "consurf": -0.475,
        "p_con": 1.0,
        "n_con": 1.0,
        "sol_acc": 29,
        "ref_prop": 2,
        "alt_prop": 0,
        "exon": 9,
        "pfam_domain": 0,
        "rel_freq": 0.0033783783783783786
    },
    "D114N": {
        "id": 74,
        "pos": 114,
        "ref": "D",
        "alt": "N",
        "target": "benign",
        "count": 1,
        "n_pos": 494,
        "d_to_active_site": 76.25995635986328,
        "d_to_ATP_site": 88.12250518798828,
        "d_to_mg_site_1": 74.09196472167969,
        "d_to_mg_site_2": 73.83785247802734,
        "consurf": 3.253,
        "p_con": 0.813024935750205,
        "n_con": 1.0,
        "sol_acc": 118,
        "ref_prop": 0,
        "alt_prop": 1,
        "exon": 4,
        "pfam_domain": 0,
        "rel_freq": 0.0033783783783783786
    },
    "R463C": {
        "id": 75,
        "pos": 463,
        "ref": "R",
        "alt": "C",
        "target": "benign",
        "count": 65,
        "n_pos": 1541,
        "d_to_active_site": 34.152462005615234,
        "d_to_ATP_site": 24.320676803588867,
        "d_to_mg_site_1": 31.50385856628418,
        "d_to_mg_site_2": 33.64141845703125,
        "consurf": 2.976,
        "p_con": 0.7737760580563209,
        "n_con": 0.7970114807622144,
        "sol_acc": 39,
        "ref_prop": 0,
        "alt_prop": 1,
        "exon": 11,
        "pfam_domain": 1,
        "rel_freq": 0.2195945945945946
    },
    "I774V": {
        "id": 76,
        "pos": 774,
        "ref": "I",
        "alt": "V",
        "target": "benign",
        "count": 1,
        "n_pos": 2474,
        "d_to_active_site": 46.579254150390625,
        "d_to_ATP_site": 60.90593338012695,
        "d_to_mg_site_1": 47.320281982421875,
        "d_to_mg_site_2": 47.16080093383789,
        "consurf": -0.478,
        "p_con": 0.9912950054937786,
        "n_con": 1.0,
        "sol_acc": 0,
        "ref_prop": 2,
        "alt_prop": 2,
        "exon": 17,
        "pfam_domain": 0,
        "rel_freq": 0.0033783783783783786
    },
    "G1004V": {
        "id": 77,
        "pos": 1004,
        "ref": "G",
        "alt": "V",
        "target": "benign",
        "count": 1,
        "n_pos": 3165,
        "d_to_active_site": 38.47800064086914,
        "d_to_ATP_site": 52.943965911865234,
        "d_to_mg_site_1": 42.78900909423828,
        "d_to_mg_site_2": 42.995079040527344,
        "consurf": -0.162,
        "p_con": 1.0,
        "n_con": 1.0,
        "sol_acc": 201,
        "ref_prop": 2,
        "alt_prop": 2,
        "exon": 22,
        "pfam_domain": 0,
        "rel_freq": 0.0033783783783783786
    },
    "P11A": {
        "id": 79,
        "pos": 11,
        "ref": "P",
        "alt": "A",
        "target": "benign",
        "count": 1,
        "n_pos": 185,
        "d_to_active_site": 0,
        "d_to_ATP_site": 0,
        "d_to_mg_site_1": 0,
        "d_to_mg_site_2": 0,
        "consurf": 3.289,
        "p_con": 0.9357121737013954,
        "n_con": 1.0,
        "sol_acc": 0,
        "ref_prop": 2,
        "alt_prop": 2,
        "exon": 2,
        "pfam_domain": 0,
        "rel_freq": 0.0033783783783783786
    },
    "H413Y": {
        "id": 80,
        "pos": 413,
        "ref": "H",
        "alt": "Y",
        "target": "benign",
        "count": 1,
        "n_pos": 1391,
        "d_to_active_site": 32.6911735534668,
        "d_to_ATP_site": 21.098407745361328,
        "d_to_mg_site_1": 32.764949798583984,
        "d_to_mg_site_2": 33.653079986572266,
        "consurf": 0.186,
        "p_con": 0.7622526823880034,
        "n_con": 0.9792817144562681,
        "sol_acc": 9,
        "ref_prop": 1,
        "alt_prop": 1,
        "exon": 10,
        "pfam_domain": 0,
        "rel_freq": 0.0033783783783783786
    },
    "R830G": {
        "id": 81,
        "pos": 830,
        "ref": "R",
        "alt": "G",
        "target": "benign",
        "count": 1,
        "n_pos": 2642,
        "d_to_active_site": 24.37864112854004,
        "d_to_ATP_site": 38.50604248046875,
        "d_to_mg_site_1": 27.418258666992188,
        "d_to_mg_site_2": 26.290996551513672,
        "consurf": 3.3,
        "p_con": 0.585886540711259,
        "n_con": 0.9109965519303428,
        "sol_acc": 26,
        "ref_prop": 0,
        "alt_prop": 2,
        "exon": 18,
        "pfam_domain": 1,
        "rel_freq": 0.0033783783783783786
    },
    "R254C": {
        "id": 82,
        "pos": 254,
        "ref": "R",
        "alt": "C",
        "target": "benign",
        "count": 1,
        "n_pos": 914,
        "d_to_active_site": 35.357364654541016,
        "d_to_ATP_site": 35.45616912841797,
        "d_to_mg_site_1": 28.004058837890625,
        "d_to_mg_site_2": 29.74131202697754,
        "consurf": -0.168,
        "p_con": 0.9844463990879841,
        "n_con": 1.0,
        "sol_acc": 1,
        "ref_prop": 0,
        "alt_prop": 1,
        "exon": 8,
        "pfam_domain": 1,
        "rel_freq": 0.0033783783783783786
    },
    "V422A": {
        "id": 83,
        "pos": 422,
        "ref": "V",
        "alt": "A",
        "target": "benign",
        "count": 4,
        "n_pos": 1419,
        "d_to_active_site": 23.321748733520508,
        "d_to_ATP_site": 13.717900276184082,
        "d_to_mg_site_1": 21.12736701965332,
        "d_to_mg_site_2": 22.63981056213379,
        "consurf": 1.156,
        "p_con": 0.8289989279126597,
        "n_con": 0.9585779998728216,
        "sol_acc": 1,
        "ref_prop": 2,
        "alt_prop": 2,
        "exon": 10,
        "pfam_domain": 1,
        "rel_freq": 0.013513513513513514
    },
    "G16S": {
        "id": 84,
        "pos": 16,
        "ref": "G",
        "alt": "S",
        "target": "benign",
        "count": 1,
        "n_pos": 200,
        "d_to_active_site": 0,
        "d_to_ATP_site": 0,
        "d_to_mg_site_1": 0,
        "d_to_mg_site_2": 0,
        "consurf": 3.3,
        "p_con": 0.9078052051429096,
        "n_con": 1.0,
        "sol_acc": 0,
        "ref_prop": 2,
        "alt_prop": 1,
        "exon": 2,
        "pfam_domain": 0,
        "rel_freq": 0.0033783783783783786
    },
    "S405L": {
        "id": 85,
        "pos": 405,
        "ref": "S",
        "alt": "L",
        "target": "benign",
        "count": 1,
        "n_pos": 1368,
        "d_to_active_site": 37.22096252441406,
        "d_to_ATP_site": 30.36507797241211,
        "d_to_mg_site_1": 37.86531066894531,
        "d_to_mg_site_2": 40.40587615966797,
        "consurf": -0.536,
        "p_con": 1.0,
        "n_con": 1.0,
        "sol_acc": 85,
        "ref_prop": 1,
        "alt_prop": 2,
        "exon": 10,
        "pfam_domain": 0,
        "rel_freq": 0.0033783783783783786
    },
    "D659N": {
        "id": 86,
        "pos": 659,
        "ref": "D",
        "alt": "N",
        "target": "benign",
        "count": 1,
        "n_pos": 2129,
        "d_to_active_site": 14.566100120544434,
        "d_to_ATP_site": 13.806356430053711,
        "d_to_mg_site_1": 20.847713470458984,
        "d_to_mg_site_2": 17.24458122253418,
        "consurf": -0.017,
        "p_con": 0.960929578020822,
        "n_con": 1.0,
        "sol_acc": 38,
        "ref_prop": 0,
        "alt_prop": 1,
        "exon": 15,
        "pfam_domain": 0,
        "rel_freq": 0.0033783783783783786
    },
    "V990I": {
        "id": 87,
        "pos": 990,
        "ref": "V",
        "alt": "I",
        "target": "benign",
        "count": 2,
        "n_pos": 3122,
        "d_to_active_site": 52.465694427490234,
        "d_to_ATP_site": 67.63140869140625,
        "d_to_mg_site_1": 54.44029998779297,
        "d_to_mg_site_2": 54.985252380371094,
        "consurf": 0.219,
        "p_con": 0.9712229955193158,
        "n_con": 0.7961377857428815,
        "sol_acc": 40,
        "ref_prop": 2,
        "alt_prop": 2,
        "exon": 22,
        "pfam_domain": 1,
        "rel_freq": 0.006756756756756757
    },
    "R492Q": {
        "id": 88,
        "pos": 492,
        "ref": "R",
        "alt": "Q",
        "target": "benign",
        "count": 2,
        "n_pos": 1629,
        "d_to_active_site": 44.15762710571289,
        "d_to_ATP_site": 30.394603729248047,
        "d_to_mg_site_1": 43.61997985839844,
        "d_to_mg_site_2": 43.72749328613281,
        "consurf": 1.095,
        "p_con": 0.8895169677362416,
        "n_con": 1.0,
        "sol_acc": 91,
        "ref_prop": 0,
        "alt_prop": 1,
        "exon": 12,
        "pfam_domain": 1,
        "rel_freq": 0.006756756756756757
    },
    "G1004E": {
        "id": 89,
        "pos": 1004,
        "ref": "G",
        "alt": "E",
        "target": "benign",
        "count": 1,
        "n_pos": 3165,
        "d_to_active_site": 38.47800064086914,
        "d_to_ATP_site": 52.943965911865234,
        "d_to_mg_site_1": 42.78900909423828,
        "d_to_mg_site_2": 42.995079040527344,
        "consurf": -0.162,
        "p_con": 1.0,
        "n_con": 1.0,
        "sol_acc": 201,
        "ref_prop": 2,
        "alt_prop": 0,
        "exon": 22,
        "pfam_domain": 0,
        "rel_freq": 0.0033783783783783786
    },
    "D490N": {
        "id": 90,
        "pos": 490,
        "ref": "D",
        "alt": "N",
        "target": "benign",
        "count": 1,
        "n_pos": 1622,
        "d_to_active_site": 42.65953063964844,
        "d_to_ATP_site": 29.678442001342773,
        "d_to_mg_site_1": 41.22380828857422,
        "d_to_mg_site_2": 41.94328308105469,
        "consurf": 0.805,
        "p_con": 0.9423162265780076,
        "n_con": 0.8780326960103101,
        "sol_acc": 62,
        "ref_prop": 0,
        "alt_prop": 1,
        "exon": 12,
        "pfam_domain": 1,
        "rel_freq": 0.0033783783783783786
    },
    "R217C": {
        "id": 91,
        "pos": 217,
        "ref": "R",
        "alt": "C",
        "target": "benign",
        "count": 1,
        "n_pos": 803,
        "d_to_active_site": 23.375015258789062,
        "d_to_ATP_site": 19.58322525024414,
        "d_to_mg_site_1": 20.002836227416992,
        "d_to_mg_site_2": 15.96388053894043,
        "consurf": -0.515,
        "p_con": 1.0,
        "n_con": 1.0,
        "sol_acc": 60,
        "ref_prop": 0,
        "alt_prop": 1,
        "exon": 7,
        "pfam_domain": 1,
        "rel_freq": 0.0033783783783783786
    },
    "K13T": {
        "id": 92,
        "pos": 13,
        "ref": "K",
        "alt": "T",
        "target": "benign",
        "count": 1,
        "n_pos": 192,
        "d_to_active_site": 0,
        "d_to_ATP_site": 0,
        "d_to_mg_site_1": 0,
        "d_to_mg_site_2": 0,
        "consurf": 1.0,
        "p_con": 0.9767803738101648,
        "n_con": 0.9780296606466663,
        "sol_acc": 0,
        "ref_prop": 0,
        "alt_prop": 1,
        "exon": 2,
        "pfam_domain": 0,
        "rel_freq": 0.0033783783783783786
    },
    "P471T": {
        "id": 93,
        "pos": 471,
        "ref": "P",
        "alt": "T",
        "target": "benign",
        "count": 1,
        "n_pos": 1565,
        "d_to_active_site": 31.189626693725586,
        "d_to_ATP_site": 17.692176818847656,
        "d_to_mg_site_1": 28.638416290283203,
        "d_to_mg_site_2": 27.651840209960938,
        "consurf": -0.487,
        "p_con": 1.0,
        "n_con": 0.9792817144562681,
        "sol_acc": 17,
        "ref_prop": 2,
        "alt_prop": 1,
        "exon": 11,
        "pfam_domain": 1,
        "rel_freq": 0.0033783783783783786
    },
    "R830Q": {
        "id": 94,
        "pos": 830,
        "ref": "R",
        "alt": "Q",
        "target": "benign",
        "count": 8,
        "n_pos": 2643,
        "d_to_active_site": 24.37864112854004,
        "d_to_ATP_site": 38.50604248046875,
        "d_to_mg_site_1": 27.418258666992188,
        "d_to_mg_site_2": 26.290996551513672,
        "consurf": 3.3,
        "p_con": 0.585886540711259,
        "n_con": 0.8023377628718116,
        "sol_acc": 26,
        "ref_prop": 0,
        "alt_prop": 1,
        "exon": 18,
        "pfam_domain": 1,
        "rel_freq": 0.02702702702702703
    },
    "E905D": {
        "id": 95,
        "pos": 905,
        "ref": "E",
        "alt": "D",
        "target": "benign",
        "count": 4,
        "n_pos": 2869,
        "d_to_active_site": 73.52238464355469,
        "d_to_ATP_site": 87.53351593017578,
        "d_to_mg_site_1": 73.01895904541016,
        "d_to_mg_site_2": 73.2615966796875,
        "consurf": -0.509,
        "p_con": 1.0,
        "n_con": 0.9487362736311753,
        "sol_acc": 8,
        "ref_prop": 0,
        "alt_prop": 0,
        "exon": 20,
        "pfam_domain": 1,
        "rel_freq": 0.013513513513513514
    },
    "P471L": {
        "id": 96,
        "pos": 471,
        "ref": "P",
        "alt": "L",
        "target": "benign",
        "count": 1,
        "n_pos": 1566,
        "d_to_active_site": 31.189626693725586,
        "d_to_ATP_site": 17.692176818847656,
        "d_to_mg_site_1": 28.638416290283203,
        "d_to_mg_site_2": 27.651840209960938,
        "consurf": -0.487,
        "p_con": 1.0,
        "n_con": 1.0,
        "sol_acc": 17,
        "ref_prop": 2,
        "alt_prop": 2,
        "exon": 11,
        "pfam_domain": 1,
        "rel_freq": 0.0033783783783783786
    },
    "V311I": {
        "id": 97,
        "pos": 311,
        "ref": "V",
        "alt": "I",
        "target": "benign",
        "count": 1,
        "n_pos": 1085,
        "d_to_active_site": 66.9205322265625,
        "d_to_ATP_site": 78.91609191894531,
        "d_to_mg_site_1": 65.31025695800781,
        "d_to_mg_site_2": 64.68527221679688,
        "consurf": -0.475,
        "p_con": 1.0,
        "n_con": 1.0,
        "sol_acc": 52,
        "ref_prop": 2,
        "alt_prop": 2,
        "exon": 8,
        "pfam_domain": 1,
        "rel_freq": 0.0033783783783783786
    },
    "E517K": {
        "id": 98,
        "pos": 517,
        "ref": "E",
        "alt": "K",
        "target": "benign",
        "count": 1,
        "n_pos": 1703,
        "d_to_active_site": 38.28651428222656,
        "d_to_ATP_site": 27.667919158935547,
        "d_to_mg_site_1": 40.04618835449219,
        "d_to_mg_site_2": 40.635501861572266,
        "consurf": -0.509,
        "p_con": 1.0,
        "n_con": 1.0,
        "sol_acc": 127,
        "ref_prop": 0,
        "alt_prop": 0,
        "exon": 12,
        "pfam_domain": 0,
        "rel_freq": 0.0033783783783783786
    },
    "V966M": {
        "id": 99,
        "pos": 966,
        "ref": "V",
        "alt": "M",
        "target": "benign",
        "count": 2,
        "n_pos": 3050,
        "d_to_active_site": 70.25659942626953,
        "d_to_ATP_site": 84.32159423828125,
        "d_to_mg_site_1": 68.44755554199219,
        "d_to_mg_site_2": 69.90332794189453,
        "consurf": 0.278,
        "p_con": 0.8896833833843788,
        "n_con": 0.9784647588246355,
        "sol_acc": 30,
        "ref_prop": 2,
        "alt_prop": 2,
        "exon": 21,
        "pfam_domain": 1,
        "rel_freq": 0.006756756756756757
    },
    "M579L": {
        "id": 100,
        "pos": 579,
        "ref": "M",
        "alt": "L",
        "target": "benign",
        "count": 1,
        "n_pos": 1889,
        "d_to_active_site": 29.278589248657227,
        "d_to_ATP_site": 17.462696075439453,
        "d_to_mg_site_1": 30.89372444152832,
        "d_to_mg_site_2": 30.850385665893555,
        "consurf": -0.077,
        "p_con": 0.9844463990879841,
        "n_con": 1.0,
        "sol_acc": 3,
        "ref_prop": 2,
        "alt_prop": 2,
        "exon": 13,
        "pfam_domain": 0,
        "rel_freq": 0.0033783783783783786
    },
    "P219A": {
        "id": 101,
        "pos": 219,
        "ref": "P",
        "alt": "A",
        "target": "benign",
        "count": 1,
        "n_pos": 809,
        "d_to_active_site": 27.397581100463867,
        "d_to_ATP_site": 20.474132537841797,
        "d_to_mg_site_1": 23.479568481445312,
        "d_to_mg_site_2": 20.454124450683594,
        "consurf": -0.398,
        "p_con": 1.0,
        "n_con": 1.0,
        "sol_acc": 48,
        "ref_prop": 2,
        "alt_prop": 2,
        "exon": 7,
        "pfam_domain": 1,
        "rel_freq": 0.0033783783783783786
    },
    "V288L": {
        "id": 102,
        "pos": 288,
        "ref": "V",
        "alt": "L",
        "target": "benign",
        "count": 1,
        "n_pos": 1016,
        "d_to_active_site": 43.050350189208984,
        "d_to_ATP_site": 55.475276947021484,
        "d_to_mg_site_1": 42.984580993652344,
        "d_to_mg_site_2": 41.59177017211914,
        "consurf": -0.527,
        "p_con": 1.0,
        "n_con": 1.0,
        "sol_acc": 13,
        "ref_prop": 2,
        "alt_prop": 2,
        "exon": 8,
        "pfam_domain": 1,
        "rel_freq": 0.0033783783783783786
    },
    "A172T": {
        "id": 103,
        "pos": 172,
        "ref": "A",
        "alt": "T",
        "target": "benign",
        "count": 1,
        "n_pos": 668,
        "d_to_active_site": 25.647478103637695,
        "d_to_ATP_site": 25.95376205444336,
        "d_to_mg_site_1": 18.717416763305664,
        "d_to_mg_site_2": 23.03791046142578,
        "consurf": -0.472,
        "p_con": 1.0,
        "n_con": 1.0,
        "sol_acc": 44,
        "ref_prop": 2,
        "alt_prop": 1,
        "exon": 6,
        "pfam_domain": 1,
        "rel_freq": 0.0033783783783783786
    },
    "V247M": {
        "id": 104,
        "pos": 247,
        "ref": "V",
        "alt": "M",
        "target": "benign",
        "count": 6,
        "n_pos": 893,
        "d_to_active_site": 26.49220085144043,
        "d_to_ATP_site": 19.582294464111328,
        "d_to_mg_site_1": 21.172080993652344,
        "d_to_mg_site_2": 21.038034439086914,
        "consurf": 0.964,
        "p_con": 0.7385808479647877,
        "n_con": 0.7957232558327251,
        "sol_acc": 6,
        "ref_prop": 2,
        "alt_prop": 2,
        "exon": 8,
        "pfam_domain": 1,
        "rel_freq": 0.02027027027027027
    },
    "R461C": {
        "id": 105,
        "pos": 461,
        "ref": "R",
        "alt": "C",
        "target": "benign",
        "count": 1,
        "n_pos": 1535,
        "d_to_active_site": 32.47117233276367,
        "d_to_ATP_site": 24.694366455078125,
        "d_to_mg_site_1": 28.814945220947266,
        "d_to_mg_site_2": 31.693359375,
        "consurf": -0.515,
        "p_con": 1.0,
        "n_con": 0.8221841762897915,
        "sol_acc": 104,
        "ref_prop": 0,
        "alt_prop": 1,
        "exon": 11,
        "pfam_domain": 1,
        "rel_freq": 0.0033783783783783786
    },
    "E629K": {
        "id": 106,
        "pos": 629,
        "ref": "E",
        "alt": "K",
        "target": "benign",
        "count": 1,
        "n_pos": 2039,
        "d_to_active_site": 20.386560440063477,
        "d_to_ATP_site": 29.286052703857422,
        "d_to_mg_site_1": 27.20410919189453,
        "d_to_mg_site_2": 27.662527084350586,
        "consurf": -0.509,
        "p_con": 1.0,
        "n_con": 1.0,
        "sol_acc": 145,
        "ref_prop": 0,
        "alt_prop": 0,
        "exon": 14,
        "pfam_domain": 0,
        "rel_freq": 0.0033783783783783786
    },
    "D820N": {
        "id": 107,
        "pos": 820,
        "ref": "D",
        "alt": "N",
        "target": "benign",
        "count": 6,
        "n_pos": 2612,
        "d_to_active_site": 30.061124801635742,
        "d_to_ATP_site": 45.64603042602539,
        "d_to_mg_site_1": 30.811689376831055,
        "d_to_mg_site_2": 32.9764289855957,
        "consurf": -0.516,
        "p_con": 1.0,
        "n_con": 1.0,
        "sol_acc": 25,
        "ref_prop": 0,
        "alt_prop": 1,
        "exon": 18,
        "pfam_domain": 1,
        "rel_freq": 0.02027027027027027
    },
    "V288M": {
        "id": 108,
        "pos": 288,
        "ref": "V",
        "alt": "M",
        "target": "benign",
        "count": 1,
        "n_pos": 1016,
        "d_to_active_site": 43.050350189208984,
        "d_to_ATP_site": 55.475276947021484,
        "d_to_mg_site_1": 42.984580993652344,
        "d_to_mg_site_2": 41.59177017211914,
        "consurf": -0.527,
        "p_con": 1.0,
        "n_con": 1.0,
        "sol_acc": 13,
        "ref_prop": 2,
        "alt_prop": 2,
        "exon": 8,
        "pfam_domain": 1,
        "rel_freq": 0.0033783783783783786
    },
    "E552Q": {
        "id": 109,
        "pos": 552,
        "ref": "E",
        "alt": "Q",
        "target": "benign",
        "count": 1,
        "n_pos": 1808,
        "d_to_active_site": 36.634239196777344,
        "d_to_ATP_site": 21.84213638305664,
        "d_to_mg_site_1": 36.60927963256836,
        "d_to_mg_site_2": 35.72325897216797,
        "consurf": 0.012,
        "p_con": 0.9912950054937786,
        "n_con": 0.8109230468143027,
        "sol_acc": 80,
        "ref_prop": 0,
        "alt_prop": 1,
        "exon": 13,
        "pfam_domain": 0,
        "rel_freq": 0.0033783783783783786
    },
    "F561S": {
        "id": 110,
        "pos": 561,
        "ref": "F",
        "alt": "S",
        "target": "benign",
        "count": 1,
        "n_pos": 1836,
        "d_to_active_site": 43.88984298706055,
        "d_to_ATP_site": 29.510013580322266,
        "d_to_mg_site_1": 41.492279052734375,
        "d_to_mg_site_2": 40.26228713989258,
        "consurf": -0.474,
        "p_con": 1.0,
        "n_con": 1.0,
        "sol_acc": 64,
        "ref_prop": 2,
        "alt_prop": 1,
        "exon": 13,
        "pfam_domain": 0,
        "rel_freq": 0.0033783783783783786
    },
    "G106S": {
        "id": 111,
        "pos": 106,
        "ref": "G",
        "alt": "S",
        "target": "benign",
        "count": 1,
        "n_pos": 470,
        "d_to_active_site": 64.1818618774414,
        "d_to_ATP_site": 75.7449722290039,
        "d_to_mg_site_1": 61.55118179321289,
        "d_to_mg_site_2": 61.47384262084961,
        "consurf": 0.735,
        "p_con": 0.770921282486753,
        "n_con": 0.978205952130997,
        "sol_acc": 105,
        "ref_prop": 2,
        "alt_prop": 1,
        "exon": 4,
        "pfam_domain": 0,
        "rel_freq": 0.0033783783783783786
    },
    "S218T": {
        "id": 112,
        "pos": 218,
        "ref": "S",
        "alt": "T",
        "target": "benign",
        "count": 1,
        "n_pos": 806,
        "d_to_active_site": 26.690492630004883,
        "d_to_ATP_site": 21.715009689331055,
        "d_to_mg_site_1": 22.83559226989746,
        "d_to_mg_site_2": 19.34482192993164,
        "consurf": -0.493,
        "p_con": 1.0,
        "n_con": 1.0,
        "sol_acc": 80,
        "ref_prop": 1,
        "alt_prop": 1,
        "exon": 7,
        "pfam_domain": 1,
        "rel_freq": 0.0033783783783783786
    },
    "G699R": {
        "id": 113,
        "pos": 699,
        "ref": "G",
        "alt": "R",
        "target": "benign",
        "count": 1,
        "n_pos": 2249,
        "d_to_active_site": 17.243209838867188,
        "d_to_ATP_site": 26.990991592407227,
        "d_to_mg_site_1": 20.8663272857666,
        "d_to_mg_site_2": 16.473913192749023,
        "consurf": -0.476,
        "p_con": 1.0,
        "n_con": 1.0,
        "sol_acc": 46,
        "ref_prop": 2,
        "alt_prop": 0,
        "exon": 16,
        "pfam_domain": 0,
        "rel_freq": 0.0033783783783783786
    },
    "N491S": {
        "id": 114,
        "pos": 491,
        "ref": "N",
        "alt": "S",
        "target": "benign",
        "count": 3,
        "n_pos": 1626,
        "d_to_active_site": 45.66754913330078,
        "d_to_ATP_site": 32.22617721557617,
        "d_to_mg_site_1": 44.5382194519043,
        "d_to_mg_site_2": 44.981868743896484,
        "consurf": 0.465,
        "p_con": 0.9215402253620955,
        "n_con": 1.0,
        "sol_acc": 141,
        "ref_prop": 1,
        "alt_prop": 1,
        "exon": 12,
        "pfam_domain": 1,
        "rel_freq": 0.010135135135135136
    },
    "R1000G": {
        "id": 115,
        "pos": 1000,
        "ref": "R",
        "alt": "G",
        "target": "benign",
        "count": 1,
        "n_pos": 3152,
        "d_to_active_site": 41.05947494506836,
        "d_to_ATP_site": 56.06778335571289,
        "d_to_mg_site_1": 44.43519973754883,
        "d_to_mg_site_2": 44.96063995361328,
        "consurf": -0.307,
        "p_con": 1.0,
        "n_con": 0.9453571426618074,
        "sol_acc": 74,
        "ref_prop": 0,
        "alt_prop": 2,
        "exon": 22,
        "pfam_domain": 0,
        "rel_freq": 0.0033783783783783786
    },
    "V29A": {
        "id": 116,
        "pos": 29,
        "ref": "V",
        "alt": "A",
        "target": "benign",
        "count": 1,
        "n_pos": 240,
        "d_to_active_site": 39.768619537353516,
        "d_to_ATP_site": 39.59925842285156,
        "d_to_mg_site_1": 34.1072998046875,
        "d_to_mg_site_2": 32.4812126159668,
        "consurf": -0.426,
        "p_con": 1.0,
        "n_con": 1.0,
        "sol_acc": 85,
        "ref_prop": 2,
        "alt_prop": 2,
        "exon": 2,
        "pfam_domain": 0,
        "rel_freq": 0.0033783783783783786
    },
    "D7N": {
        "id": 117,
        "pos": 7,
        "ref": "D",
        "alt": "N",
        "target": "benign",
        "count": 1,
        "n_pos": 173,
        "d_to_active_site": 0,
        "d_to_ATP_site": 0,
        "d_to_mg_site_1": 0,
        "d_to_mg_site_2": 0,
        "consurf": 3.296,
        "p_con": 0.8319095324118801,
        "n_con": 0.8124742967879938,
        "sol_acc": 0,
        "ref_prop": 0,
        "alt_prop": 1,
        "exon": 2,
        "pfam_domain": 0,
        "rel_freq": 0.0033783783783783786
    },
    "D571N": {
        "id": 118,
        "pos": 571,
        "ref": "D",
        "alt": "N",
        "target": "benign",
        "count": 2,
        "n_pos": 1865,
        "d_to_active_site": 34.160430908203125,
        "d_to_ATP_site": 18.639833450317383,
        "d_to_mg_site_1": 33.7952880859375,
        "d_to_mg_site_2": 31.268985748291016,
        "consurf": 1.844,
        "p_con": 0.9206088348536111,
        "n_con": 0.9793597659404568,
        "sol_acc": 12,
        "ref_prop": 0,
        "alt_prop": 1,
        "exon": 13,
        "pfam_domain": 0,
        "rel_freq": 0.006756756756756757
    },
    "N476K": {
        "id": 119,
        "pos": 476,
        "ref": "N",
        "alt": "K",
        "target": "benign",
        "count": 1,
        "n_pos": 1582,
        "d_to_active_site": 15.788320541381836,
        "d_to_ATP_site": 6.175841808319092,
        "d_to_mg_site_1": 14.268049240112305,
        "d_to_mg_site_2": 12.108292579650879,
        "consurf": -0.53,
        "p_con": 1.0,
        "n_con": 0.9223106657323543,
        "sol_acc": 30,
        "ref_prop": 1,
        "alt_prop": 0,
        "exon": 11,
        "pfam_domain": 1,
        "rel_freq": 0.0033783783783783786
    },
    "R43W": {
        "id": 120,
        "pos": 43,
        "ref": "R",
        "alt": "W",
        "target": "benign",
        "count": 1,
        "n_pos": 281,
        "d_to_active_site": 45.605369567871094,
        "d_to_ATP_site": 38.31593322753906,
        "d_to_mg_site_1": 39.51307678222656,
        "d_to_mg_site_2": 39.72779083251953,
        "consurf": -0.019,
        "p_con": 0.9844463990879841,
        "n_con": 0.8972037459074584,
        "sol_acc": 95,
        "ref_prop": 0,
        "alt_prop": 1,
        "exon": 3,
        "pfam_domain": 1,
        "rel_freq": 0.0033783783783783786
    },
    "N489K": {
        "id": 121,
        "pos": 489,
        "ref": "N",
        "alt": "K",
        "target": "benign",
        "count": 1,
        "n_pos": 1621,
        "d_to_active_site": 41.78608322143555,
        "d_to_ATP_site": 28.824804306030273,
        "d_to_mg_site_1": 39.777305603027344,
        "d_to_mg_site_2": 40.47483444213867,
        "consurf": 1.288,
        "p_con": 0.8680172253855223,
        "n_con": 0.41515682386454467,
        "sol_acc": 63,
        "ref_prop": 1,
        "alt_prop": 0,
        "exon": 12,
        "pfam_domain": 1,
        "rel_freq": 0.0033783783783783786
    },
    "R19C": {
        "id": 122,
        "pos": 19,
        "ref": "R",
        "alt": "C",
        "target": "benign",
        "count": 5,
        "n_pos": 209,
        "d_to_active_site": 0,
        "d_to_ATP_site": 0,
        "d_to_mg_site_1": 0,
        "d_to_mg_site_2": 0,
        "consurf": 3.3,
        "p_con": 0.5019053098324561,
        "n_con": 0.6834552899969302,
        "sol_acc": 0,
        "ref_prop": 0,
        "alt_prop": 1,
        "exon": 2,
        "pfam_domain": 0,
        "rel_freq": 0.016891891891891893
    },
    "A421S": {
        "id": 123,
        "pos": 421,
        "ref": "A",
        "alt": "S",
        "target": "benign",
        "count": 1,
        "n_pos": 1415,
        "d_to_active_site": 25.239290237426758,
        "d_to_ATP_site": 13.326384544372559,
        "d_to_mg_site_1": 23.619155883789062,
        "d_to_mg_site_2": 24.238496780395508,
        "consurf": -0.528,
        "p_con": 1.0,
        "n_con": 0.9792817144562681,
        "sol_acc": 0,
        "ref_prop": 2,
        "alt_prop": 1,
        "exon": 10,
        "pfam_domain": 1,
        "rel_freq": 0.0033783783783783786
    },
    "E670K": {
        "id": 124,
        "pos": 670,
        "ref": "E",
        "alt": "K",
        "target": "benign",
        "count": 1,
        "n_pos": 2162,
        "d_to_active_site": 22.10814094543457,
        "d_to_ATP_site": 25.11506462097168,
        "d_to_mg_site_1": 28.17717933654785,
        "d_to_mg_site_2": 22.993995666503906,
        "consurf": 1.282,
        "p_con": 0.7913474877440225,
        "n_con": 1.0,
        "sol_acc": 101,
        "ref_prop": 0,
        "alt_prop": 0,
        "exon": 15,
        "pfam_domain": 0,
        "rel_freq": 0.0033783783783783786
    },
    "S665P": {
        "id": 125,
        "pos": 665,
        "ref": "S",
        "alt": "P",
        "target": "benign",
        "count": 1,
        "n_pos": 2147,
        "d_to_active_site": 21.840742111206055,
        "d_to_ATP_site": 18.794218063354492,
        "d_to_mg_site_1": 26.899784088134766,
        "d_to_mg_site_2": 21.310054779052734,
        "consurf": 1.71,
        "p_con": 0.7044014192221504,
        "n_con": 0.8454898407316901,
        "sol_acc": 105,
        "ref_prop": 1,
        "alt_prop": 2,
        "exon": 15,
        "pfam_domain": 0,
        "rel_freq": 0.0033783783783783786
    }
}
